Metadata-Version: 1.1
Name: tdparser
Version: 1.1.6
Summary: A very simple parsing library, based on the Top-Down algorithm.
Home-page: http://github.com/rbarrois/tdparser
Author: Raphaël Barrois
Author-email: raphael.barrois+tdparser@polytechnique.org
License: BSD
Download-URL: http://pypi.python.org/pypi/tdparser/
Keywords: parser,lexer,token,topdown
Platform: UNKNOWN
Classifier: Development Status :: 4 - Beta
Classifier: Intended Audience :: Developers
Classifier: License :: OSI Approved :: BSD License
Classifier: Operating System :: OS Independent
Classifier: Programming Language :: Python :: 2.6
Classifier: Programming Language :: Python :: 2.7
Classifier: Programming Language :: Python :: 3
Classifier: Programming Language :: Python
Classifier: Topic :: Software Development :: Libraries :: Python Modules
